spadix_cli/__init__.py
spadix_cli/__main__.py
spadix_cli-0.7.4.dist-info/LICENSE
spadix_cli-0.7.4.dist-info/METADATA
spadix_cli-0.7.4.dist-info/WHEEL
spadix_cli-0.7.4.dist-info/entry_points.txt
spadix_cli-0.7.4.dist-info/top_level.txt
spadix_cli-0.7.4.dist-info/RECORD
