Metadata-Version: 2.1
Name: spadix-cli
Version: 0.7.4
Summary: SAF friendly wrapper for colcon
Home-page: https://safeai.ai
Author: Serge Nikulin
Author-email: serge@safeai.ai
Maintainer: Serge Nikulin
Maintainer-email: serge@safeai.ai
Project-URL: Bug Tracker, https://gitlab.safeai.ai/production/spadix-cli
Keywords: spadix-cli
Classifier: Programming Language :: Python :: 3
Classifier: License :: OSI Approved :: MIT License
Classifier: Operating System :: OS Independent
Requires-Python: >=3.6
License-File: LICENSE
Requires-Dist: setuptools
Requires-Dist: lark
